ai_runtime/__init__.py
ai_runtime/config.py
ai_runtime/downloader/__init__.py
ai_runtime/downloader/__main__.py
ai_runtime/downloader/base.py
ai_runtime/downloader/huggingface.py
ai_runtime/downloader/s3.py
ai_runtime/downloader/tos.py
ai_runtime/envs.py
ai_runtime/logger.py
ai_runtime/protos/__init__.py
ai_runtime-0.1.1rc1.dist-info/METADATA
ai_runtime-0.1.1rc1.dist-info/WHEEL
ai_runtime-0.1.1rc1.dist-info/RECORD
