Metadata-Version: 2.1
Name: ai-runtime
Version: 0.1.1rc1
Summary: 
Home-page: https://github.com/brosoul/ai_runtime/tree/main/ai_runtime
License: Apache-2.0
Author: Runtime Authors
Author-email: brosoul@126.com
Requires-Python: >=3.11,<4.0
Classifier: Intended Audience :: Developers
Classifier: Intended Audience :: Education
Classifier: Intended Audience :: Science/Research
Classifier: License :: OSI Approved :: Apache Software License
Classifier: Operating System :: OS Independent
Classifier: Programming Language :: Python :: 3
Classifier: Programming Language :: Python :: 3.11
Classifier: Programming Language :: Python :: 3.12
Classifier: Programming Language :: Python :: 3.10
Classifier: Programming Language :: Python :: 3.8
Classifier: Programming Language :: Python :: 3.9
Classifier: Topic :: Scientific/Engineering
Classifier: Topic :: Scientific/Engineering :: Artificial Intelligence
Classifier: Topic :: Software Development
Classifier: Topic :: Software Development :: Libraries
Classifier: Topic :: Software Development :: Libraries :: Python Modules
Requires-Dist: fastapi (>=0.114.0,<0.115.0)
Project-URL: Repository, https://github.com/brosoul/ai_runtime/tree/main/ai_runtime
